CHANGES.rst
CONTRIBUTORS.rst
MANIFEST.in
README.rst
setup.cfg
setup.py
docs/LICENSE.GPL
docs/LICENSE.rst
docs/index.rst
src/Products/__init__.py
src/Products.JWPlayer.egg-info/PKG-INFO
src/Products.JWPlayer.egg-info/SOURCES.txt
src/Products.JWPlayer.egg-info/dependency_links.txt
src/Products.JWPlayer.egg-info/entry_points.txt
src/Products.JWPlayer.egg-info/namespace_packages.txt
src/Products.JWPlayer.egg-info/not-zip-safe
src/Products.JWPlayer.egg-info/requires.txt
src/Products.JWPlayer.egg-info/top_level.txt
src/Products/JWPlayer/__init__.py
src/Products/JWPlayer/configure.zcml
src/Products/JWPlayer/interfaces.py
src/Products/JWPlayer/setuphandlers.py
src/Products/JWPlayer/testing.py
src/Products/JWPlayer/browser/__init__.py
src/Products/JWPlayer/browser/configure.zcml
src/Products/JWPlayer/browser/jwplayer.py
src/Products/JWPlayer/browser/overrides/.gitkeep
src/Products/JWPlayer/browser/static/.gitkeep
src/Products/JWPlayer/browser/static/ProductsJWPlayer.js
src/Products/JWPlayer/browser/static/dummy.gif
src/Products/JWPlayer/browser/static/icon.gif
src/Products/JWPlayer/browser/static/jw.jpg
src/Products/JWPlayer/browser/static/popup.css
src/Products/JWPlayer/browser/static/popup.js
src/Products/JWPlayer/browser/static/site.css
src/Products/JWPlayer/browser/static/site.js
src/Products/JWPlayer/browser/static/tinymce.js
src/Products/JWPlayer/browser/static/video.gif
src/Products/JWPlayer/browser/templates/jwp-tinymce-settings.pt
src/Products/JWPlayer/locales/Products.JWPlayer.pot
src/Products/JWPlayer/locales/rebuild.sh
src/Products/JWPlayer/locales/update.sh
src/Products/JWPlayer/locales/de/LC_MESSAGES/Products.JWPlayer.mo
src/Products/JWPlayer/locales/de/LC_MESSAGES/Products.JWPlayer.po
src/Products/JWPlayer/locales/en/LC_MESSAGES/Products.JWPlayer.mo
src/Products/JWPlayer/locales/en/LC_MESSAGES/Products.JWPlayer.po
src/Products/JWPlayer/profiles/default/browserlayer.xml
src/Products/JWPlayer/profiles/default/cssregistry.xml
src/Products/JWPlayer/profiles/default/jsregistry.xml
src/Products/JWPlayer/profiles/default/metadata.xml
src/Products/JWPlayer/profiles/default/registry.xml
src/Products/JWPlayer/profiles/default/tinymce.xml
src/Products/JWPlayer/profiles/uninstall/browserlayer.xml
src/Products/JWPlayer/profiles/uninstall/cssregistry.xml
src/Products/JWPlayer/profiles/uninstall/jsregistry.xml
