Metadata-Version: 1.1
Name: Products.JWPlayer
Version: 1.1
Summary: JWPlayer add-on for Plone 4. Embed videos using TinyMCE to be played with the jwplayer
Home-page: https://github.com/cyriltata/Products.JWPlayer
Author: Cyril Tata
Author-email: cyril.tata@gmail.com
License: GPL version 2
Download-URL: https://github.com/cyriltata/Products.JWPlayer/archive/1.1.tar.gz
Keywords: Python Plone jwplayer tinymce Products.TinyMCE
Platform: UNKNOWN
Classifier: Environment :: Web Environment
Classifier: Framework :: Plone
Classifier: Framework :: Plone :: 4.3
Classifier: Programming Language :: Python
Classifier: Programming Language :: Python :: 2.7
Classifier: Operating System :: OS Independent
Classifier: License :: OSI Approved :: GNU General Public License v2 (GPLv2)
